py_openocd_client/__init__.py
py_openocd_client/baseclient.py
py_openocd_client/bp_parser.py
py_openocd_client/client.py
py_openocd_client/errors.py
py_openocd_client/types.py
py_openocd_client/wp_parser.py
PyOpenocdClient-0.1.0.dist-info/LICENSE
PyOpenocdClient-0.1.0.dist-info/METADATA
PyOpenocdClient-0.1.0.dist-info/WHEEL
PyOpenocdClient-0.1.0.dist-info/top_level.txt
PyOpenocdClient-0.1.0.dist-info/RECORD
