Metadata-Version: 2.1
Name: PyOpenocdClient
Version: 0.1.0
Summary: Library for controlling OpenOCD from Python programs
Author-email: Jan Matyas <info@janmatyas.net>
Project-URL: Homepage, https://github.com/HonzaMat/PyOpenocdClient
Project-URL: Issues, https://github.com/HonzaMat/PyOpenocdClient/issues
Project-URL: Documentation, https://pyopenocdclient.readthedocs.io/en/latest/
Classifier: Programming Language :: Python :: 3
Classifier: License :: OSI Approved :: MIT License
Classifier: Operating System :: OS Independent
Requires-Python: >=3.7
License-File: LICENSE
